__init__.py
exactpy/__init__.py
exactpy/auth.py
exactpy/client.py
exactpy/exceptions.py
exactpy/alias_generators/__init__.py
exactpy/controllers/__init__.py
exactpy/controllers/base.py
exactpy/controllers/crm/__init__.py
exactpy/controllers/crm/account.py
exactpy/controllers/financial/__init__.py
exactpy/controllers/financial/aging_overview.py
exactpy/controllers/financial/aging_payables_receivables_list.py
exactpy/controllers/financial/deductibility_percentage.py
exactpy/controllers/financial/exchange_rate.py
exactpy/controllers/financial/financial_period.py
exactpy/controllers/financial/gl_account.py
exactpy/controllers/financial/gl_account_classification_mappings.py
exactpy/controllers/financial/gl_scheme.py
exactpy/controllers/financial/gl_transaction_source.py
exactpy/controllers/financial/gl_transaction_type.py
exactpy/controllers/financial/journal.py
exactpy/controllers/financial/journal_status_list.py
exactpy/controllers/financial/official_returns.py
exactpy/controllers/financial/outstanding_invoices_overview.py
exactpy/controllers/financial/payables_receivables_list.py
exactpy/controllers/financial/profit_loss_overview.py
exactpy/controllers/financial/reporting_balance.py
exactpy/controllers/financial/reporting_balance_by_classification.py
exactpy/controllers/financial/returns.py
exactpy/controllers/financial/revenue_list.py
exactpy/controllers/system/__init__.py
exactpy/controllers/system/division.py
exactpy/controllers/system/me.py
exactpy/models/__init__.py
exactpy/models/base.py
exactpy/models/query.py
exactpy/models/validation.py
exactpy/models/crm/__init__.py
exactpy/models/crm/account.py
exactpy/models/crm/bank_account.py
exactpy/models/financial/__init__.py
exactpy/models/financial/aging_overview.py
exactpy/models/financial/aging_payables_receivables_list.py
exactpy/models/financial/deductibility_percentage.py
exactpy/models/financial/exchange_rate.py
exactpy/models/financial/financial_period.py
exactpy/models/financial/gl_account.py
exactpy-0.0.23.dist-info/licenses/LICENSE
exactpy-0.0.23.dist-info/METADATA
exactpy-0.0.23.dist-info/WHEEL
exactpy-0.0.23.dist-info/top_level.txt
exactpy-0.0.23.dist-info/RECORD
