Metadata-Version: 2.4
Name: exactpy
Version: 0.0.23
Summary: Modern Python interface to the exact online API
Requires-Python: >=3.10
License-File: LICENSE
Requires-Dist: azure-keyvault-secrets>=4.10.0
Requires-Dist: commitizen>=4.9.1
Requires-Dist: httpx>=0.28.1
Requires-Dist: httpx-retries>=0.4.5
Requires-Dist: loguru>=0.7.3
Requires-Dist: pydantic>=2.12.0
Requires-Dist: requests-oauthlib>=2.0.0
Requires-Dist: sparkdantic>=2.6.0
Provides-Extra: pandas
Provides-Extra: pyspark
Requires-Dist: pyspark>=4.0.1; extra == "pyspark"
Dynamic: license-file
